QRankGWAS/QRankGWAS.py
QRankGWAS/__init__.py
QRankGWAS/__main__.py
QRankGWAS-0.0.9.dist-info/LICENSE
QRankGWAS-0.0.9.dist-info/METADATA
QRankGWAS-0.0.9.dist-info/WHEEL
QRankGWAS-0.0.9.dist-info/entry_points.txt
QRankGWAS-0.0.9.dist-info/top_level.txt
QRankGWAS-0.0.9.dist-info/RECORD
