Metadata-Version: 2.1
Name: QRankGWAS
Version: 0.0.9
Summary: Python implementation of the QRank method described in Song et al Bioninformatics 2017.
Home-page: https://github.com/daverblair/QRankGWAS
Author: David Blair
Author-email: david.blair@ucsf.edu
License: UNKNOWN
Platform: UNKNOWN
Classifier: Programming Language :: Python :: 3
Classifier: License :: OSI Approved :: MIT License
Classifier: Operating System :: OS Independent
Requires-Dist: argparse (>=1.1)
Requires-Dist: numpy (>=1.19.0)
Requires-Dist: pandas (>=1.0.5)
Requires-Dist: statsmodels (>=0.11.1)
Requires-Dist: scipy (>=1.5.2)
Requires-Dist: scikit-learn (>=0.22.1)
Requires-Dist: bgen (==1.2.7)
